amaranth-0.6.0.dist-info/METADATA
amaranth-0.6.0.dist-info/WHEEL
amaranth-0.6.0.dist-info/entry_points.txt
amaranth-0.6.0.dist-info/licenses/LICENSE.txt
amaranth/__init__.py
amaranth/_toolchain/__init__.py
amaranth/_toolchain/yosys.py
amaranth/_unused.py
amaranth/_utils.py
amaranth/asserts.py
amaranth/back/__init__.py
amaranth/back/cxxrtl.py
amaranth/back/rtlil.py
amaranth/back/verilog.py
amaranth/build/__init__.py
amaranth/build/dsl.py
amaranth/build/plat.py
amaranth/build/res.py
amaranth/build/run.py
amaranth/cli.py
amaranth/hdl/__init__.py
amaranth/hdl/_ast.py
amaranth/hdl/_cd.py
amaranth/hdl/_dsl.py
amaranth/hdl/_ir.py
amaranth/hdl/_mem.py
amaranth/hdl/_nir.py
amaranth/hdl/_rec.py
amaranth/hdl/_xfrm.py
amaranth/hdl/ast.py
amaranth/hdl/cd.py
amaranth/hdl/dsl.py
amaranth/hdl/ir.py
amaranth/hdl/mem.py
amaranth/hdl/rec.py
amaranth/hdl/xfrm.py
amaranth/lib/__init__.py
amaranth/lib/cdc.py
amaranth/lib/coding.py
amaranth/lib/crc/__init__.py
amaranth/lib/crc/catalog.py
amaranth/lib/data.py
amaranth/lib/enum.py
amaranth/lib/fifo.py
amaranth/lib/io.py
amaranth/lib/memory.py
amaranth/lib/meta.py
amaranth/lib/stream.py
amaranth/lib/wiring.py
amaranth/rpc.py
amaranth/sim/__init__.py
amaranth/sim/_async.py
amaranth/sim/_base.py
amaranth/sim/_pyclock.py
amaranth/sim/_pycoro.py
amaranth/sim/_pyeval.py
amaranth/sim/_pyrtl.py
amaranth/sim/core.py
amaranth/sim/pysim.py
amaranth/tracer.py
amaranth/utils.py
amaranth/vendor/__init__.py
amaranth/vendor/_altera.py
amaranth/vendor/_gowin.py
amaranth/vendor/_lattice.py
amaranth/vendor/_quicklogic.py
amaranth/vendor/_siliconblue.py
amaranth/vendor/_xilinx.py
amaranth-0.6.0.dist-info/RECORD
