Metadata-Version: 2.1
Name: amaranth
Version: 0.6.0
Summary: Amaranth hardware definition language
Author: Amaranth HDL contributors
License: BSD-2-clause
Project-URL: Homepage, https://amaranth-lang.org/
Project-URL: Documentation, https://amaranth-lang.org/docs/amaranth/v0.6.0v0.6.0
Project-URL: Source code, https://github.com/amaranth-lang/amaranth
Project-URL: Bug tracker, https://github.com/amaranth-lang/amaranth/issues
Requires-Python: ~=3.8
Requires-Dist: importlib_resources; python_version < "3.9"
Requires-Dist: jschon~=0.11.1
Requires-Dist: pyvcd<0.5,>=0.2.2
Requires-Dist: Jinja2~=3.0
Requires-Dist: amaranth-yosys>=0.40; extra == "builtin-yosys"
Requires-Dist: paramiko~=2.7; extra == "remote-build"
Provides-Extra: builtin-yosys
Provides-Extra: remote-build
